tbskmodem/__init__.py
tbskmodem/__main__.py
tbskmodem/kokolink/interfaces.py
tbskmodem/kokolink/filter/AggregateFilter.py
tbskmodem/kokolink/filter/Bits2BytesFilter.py
tbskmodem/kokolink/filter/Bits2StrFilter.py
tbskmodem/kokolink/filter/BitsWidthFilter.py
tbskmodem/kokolink/filter/ReplaceFilter.py
tbskmodem/kokolink/filter/__init__.py
tbskmodem/kokolink/io/__init__.py
tbskmodem/kokolink/io/reedsolomon.py
tbskmodem/kokolink/io/audio/__init__.py
tbskmodem/kokolink/io/audio/audioif.py
tbskmodem/kokolink/io/audio/pyaudioio.py
tbskmodem/kokolink/io/audio/sddeviceaudio.py
tbskmodem/kokolink/protocol/tbsk/AlgorithmSwitch.py
tbskmodem/kokolink/protocol/tbsk/tbskmodem.py
tbskmodem/kokolink/protocol/tbsk/toneblock.py
tbskmodem/kokolink/protocol/tbsk/traitblockcoder.py
tbskmodem/kokolink/protocol/tbsk/preamble/CoffPreamble.py
tbskmodem/kokolink/protocol/tbsk/preamble/Preamble.py
tbskmodem/kokolink/protocol/tbsk/preamble/__init__.py
tbskmodem/kokolink/streams/BitStream.py
tbskmodem/kokolink/streams/ByteStream.py
tbskmodem/kokolink/streams/ChaindStream.py
tbskmodem/kokolink/streams/RoStream.py
tbskmodem/kokolink/streams/__init__.py
tbskmodem/kokolink/streams/bytestreams.py
tbskmodem/kokolink/streams/rostreams.py
tbskmodem/kokolink/toolbox/__init__.py
tbskmodem/kokolink/toolbox/soundkit.py
tbskmodem/kokolink/types/__init__.py
tbskmodem/kokolink/utils/AsyncMethod.py
tbskmodem/kokolink/utils/BitsWidthConvertIterator.py
tbskmodem/kokolink/utils/BufferedIterator.py
tbskmodem/kokolink/utils/FloatConverter.py
tbskmodem/kokolink/utils/RecordableIterator.py
tbskmodem/kokolink/utils/RingBuffer.py
tbskmodem/kokolink/utils/__init__.py
tbskmodem/kokolink/utils/debuglogger.py
tbskmodem/kokolink/utils/eventlog.py
tbskmodem/kokolink/utils/functions.py
tbskmodem/kokolink/utils/indexsequence.py
tbskmodem/kokolink/utils/recoverable.py
tbskmodem/kokolink/utils/serializable.py
tbskmodem/kokolink/utils/math/AverageInterator.py
tbskmodem/kokolink/utils/math/GrayCode.py
tbskmodem-0.3.7.dist-info/LICENSE
tbskmodem-0.3.7.dist-info/METADATA
tbskmodem-0.3.7.dist-info/WHEEL
tbskmodem-0.3.7.dist-info/entry_points.txt
tbskmodem-0.3.7.dist-info/top_level.txt
tbskmodem-0.3.7.dist-info/RECORD
