Metadata-Version: 2.1
Name: tbskmodem
Version: 0.3.7
Summary: Trait block shift keying modem.
Project-URL: homepage, https://github.com/nyatla/TBSKmodem/
Classifier: Intended Audience :: Developers
Classifier: Programming Language :: Python :: 3
Classifier: Topic :: Software Development :: Libraries :: Python Modules
License-File: LICENSE
